switch_profile/__init__.py
switch_profile/app.py
switch_profile/scripts/assume-role.sh
switch_aws_profile-0.0.6.dist-info/LICENSE
switch_aws_profile-0.0.6.dist-info/METADATA
switch_aws_profile-0.0.6.dist-info/WHEEL
switch_aws_profile-0.0.6.dist-info/entry_points.txt
switch_aws_profile-0.0.6.dist-info/top_level.txt
switch_aws_profile-0.0.6.dist-info/RECORD
