Metadata-Version: 2.1
Name: switch-aws-profile
Version: 0.0.6
Summary: Switch AWS profile on local
Home-page: https://github.com/kimisme9386/cli-switch-aws-profile
Author: Chris Yang
Author-email: kimisme9386@gmail.com
License: MIT
Classifier: Programming Language :: Python :: 3.8
Classifier: Operating System :: OS Independent
Requires-Python: >=3.7
License-File: LICENSE
Requires-Dist: pyinquirer (==1.0.3)
